astra_tl_new-1.1.0.dist-info/licenses/LICENSE.md
astratl/__init__.py
astratl/custom.py
astratl/functions.py
astratl/helpers.py
astratl/hints.py
astratl/password.py
astratl/requestiter.py
astratl/sync.py
astratl/types.py
astratl/utils.py
astratl/version.py
astratl/_updates/__init__.py
astratl/_updates/entitycache.py
astratl/_updates/messagebox.py
astratl/_updates/session.py
astratl/client/__init__.py
astratl/client/account.py
astratl/client/auth.py
astratl/client/bots.py
astratl/client/buttons.py
astratl/client/chats.py
astratl/client/dialogs.py
astratl/client/downloads.py
astratl/client/messageparse.py
astratl/client/messages.py
astratl/client/telegrambaseclient.py
astratl/client/telegramclient.py
astratl/client/updates.py
astratl/client/uploads.py
astratl/client/users.py
astratl/crypto/__init__.py
astratl/crypto/aes.py
astratl/crypto/aesctr.py
astratl/crypto/authkey.py
astratl/crypto/cdndecrypter.py
astratl/crypto/factorization.py
astratl/crypto/libssl.py
astratl/crypto/rsa.py
astratl/errors/__init__.py
astratl/errors/common.py
astratl/errors/rpcbaseerrors.py
astratl/errors/rpcerrorlist.py
astratl/events/__init__.py
astratl/events/album.py
astratl/events/callbackquery.py
astratl/events/chataction.py
astratl/events/common.py
astratl/events/inlinequery.py
astratl/events/messagedeleted.py
astratl/events/messageedited.py
astratl/events/messageread.py
astratl/events/newmessage.py
astratl/events/raw.py
astratl/events/userupdate.py
astratl/extensions/__init__.py
astratl/extensions/binaryreader.py
astratl/extensions/html.py
astratl/extensions/markdown.py
astratl/extensions/messagepacker.py
astratl/network/__init__.py
astratl/network/authenticator.py
astratl/network/mtprotoplainsender.py
astratl/network/mtprotosender.py
astratl/network/mtprotostate.py
astratl/network/requeststate.py
astratl/network/connection/__init__.py
astratl/network/connection/connection.py
astratl/network/connection/http.py
astratl/network/connection/tcpabridged.py
astratl/network/connection/tcpfull.py
astratl/network/connection/tcpintermediate.py
astra_tl_new-1.1.0.dist-info/METADATA
astra_tl_new-1.1.0.dist-info/WHEEL
astra_tl_new-1.1.0.dist-info/top_level.txt
astra_tl_new-1.1.0.dist-info/RECORD
