Metadata-Version: 2.4
Name: astra-tl-new
Version: 1.1.0
Summary: This library is built for the Astra userbot and is based on Telethon.
Home-page: https://github.com/lovpq/astra-tl
Download-URL: https://pypi.org/project/astra-tl-new/
Author: lovpq
Author-email: lovpqq@gmail.com
License: CCBYNCND V4
Keywords: telegram api chat client library messaging mtproto
Classifier: Development Status :: 5 - Production/Stable
Classifier: Intended Audience :: Developers
Classifier: Topic :: Communications :: Chat
Classifier: License :: OSI Approved :: MIT License
Classifier: Programming Language :: Python :: 3
Classifier: Programming Language :: Python :: 3.5
Classifier: Programming Language :: Python :: 3.6
Classifier: Programming Language :: Python :: 3.7
Classifier: Programming Language :: Python :: 3.8
Requires-Python: >=3.5
License-File: LICENSE.md
Requires-Dist: pyaes
Requires-Dist: aiofile==3.8.1
Requires-Dist: aiofiles==24.1.0
Requires-Dist: gitpython==3.1.27
Requires-Dist: meval==2.5
Requires-Dist: aiohttp_jinja2==1.5
Requires-Dist: aiohttp==3.11.18
Requires-Dist: Jinja2==3.0.3
Requires-Dist: requests==2.27.1
Requires-Dist: aiogram==3.20.0
Requires-Dist: grapheme==0.6.0
Requires-Dist: emoji==2.1.0
Requires-Dist: werkzeug==2.2.2
Requires-Dist: psutil==6.0.0
Requires-Dist: tgcrypto==1.2.5
Requires-Dist: rsa==4.9
Requires-Dist: ruamel.yaml==0.17.21
Requires-Dist: bs4==0.0.2
Provides-Extra: cryptg
Requires-Dist: cryptg; extra == "cryptg"
Dynamic: author
Dynamic: author-email
Dynamic: classifier
Dynamic: description
Dynamic: description-content-type
Dynamic: download-url
Dynamic: home-page
Dynamic: keywords
Dynamic: license
Dynamic: license-file
Dynamic: provides-extra
Dynamic: requires-dist
Dynamic: requires-python
Dynamic: summary
